metaplex/__init__.py
metaplex/metadata.py
metaplex/transactions.py
metaplex_python_api-1.5.0.dist-info/METADATA
metaplex_python_api-1.5.0.dist-info/WHEEL
metaplex_python_api-1.5.0.dist-info/top_level.txt
metaplex_python_api-1.5.0.dist-info/RECORD
