Metadata-Version: 2.1
Name: metaplex-python-api
Version: 1.5.0
Requires-Python: >=3.8
Requires-Dist: anyio >=3.3.4
Requires-Dist: attrs >=21.2.0
Requires-Dist: base58 >=2.1.1
Requires-Dist: cachetools >=4.2.4
Requires-Dist: certifi >=2021.10.8
Requires-Dist: cffi >=1.15.0
Requires-Dist: chardet >=4.0.0
Requires-Dist: charset-normalizer >=2.0.7
Requires-Dist: cheroot >=8.5.2
Requires-Dist: CherryPy >=18.6.1
Requires-Dist: construct >=2.10.67
Requires-Dist: cryptography >=35.0.0
Requires-Dist: ed25519 >=1.5
Requires-Dist: h11 >=0.12.0
Requires-Dist: httpcore >=0.13.7
Requires-Dist: httpx >=0.20.0
Requires-Dist: idna >=3.3
Requires-Dist: iniconfig >=1.1.1
Requires-Dist: jaraco.classes >=3.2.1
Requires-Dist: jaraco.collections >=3.4.0
Requires-Dist: jaraco.functools >=3.3.0
Requires-Dist: jaraco.text >=3.5.1
Requires-Dist: more-itertools >=8.10.0
Requires-Dist: packaging >=21.2
Requires-Dist: pluggy >=1.0.0
Requires-Dist: portend >=3.0.0
Requires-Dist: py >=1.10.0
Requires-Dist: pycparser >=2.20
Requires-Dist: PyNaCl >=1.4.0
Requires-Dist: pyparsing >=2.4.7
Requires-Dist: pytest >=6.2.5
Requires-Dist: pytz >=2021.3
Requires-Dist: requests >=2.26.0
Requires-Dist: rfc3986 >=1.5.0
Requires-Dist: six >=1.16.0
Requires-Dist: sniffio >=1.2.0
Requires-Dist: solana ==0.18.1
Requires-Dist: tempora >=4.1.2
Requires-Dist: toml >=0.10.2
Requires-Dist: typing-extensions >=3.10.0.2
Requires-Dist: urllib3 >=1.26.7
Requires-Dist: websockets >=10.0
Requires-Dist: zc.lockfile >=2.0
